todo_manager/__init__.py
todo_manager/cli.py
todo_manager/core.py
todo_manager/data_handler.py
todo_manager/utils.py
TickBox-1.0.0.dist-info/LICENSE
TickBox-1.0.0.dist-info/METADATA
TickBox-1.0.0.dist-info/WHEEL
TickBox-1.0.0.dist-info/entry_points.txt
TickBox-1.0.0.dist-info/top_level.txt
TickBox-1.0.0.dist-info/RECORD
